mm_test_adapters/__init__.py
mm_test_adapters/version.py
mm_test_adapters/libs/MMConfig_demo.cfg
mm_test_adapters/libs/libmmgr_dal_DemoCamera.so.0
mm_test_adapters/libs/libmmgr_dal_NotificationTester.so.0
mm_test_adapters/libs/libmmgr_dal_SequenceTester.so.0
mm_test_adapters/libs/libmmgr_dal_Utilities.so.0
mm_test_adapters-74.20260129.dist-info/METADATA
mm_test_adapters-74.20260129.dist-info/WHEEL
mm_test_adapters-74.20260129.dist-info/top_level.txt
mm_test_adapters-74.20260129.dist-info/RECORD
