Metadata-Version: 2.4
Name: mm-test-adapters
Version: 74.20260129
Requires-Python: >=3.9
